BythonJ/BYAssociation.py
BythonJ/BythonJ.py
BythonJ/Errors.py
BythonJ/__init__.py
BythonJ/data/keywords.txt
BythonJ-1.2.9.dist-info/METADATA
BythonJ-1.2.9.dist-info/WHEEL
BythonJ-1.2.9.dist-info/entry_points.txt
BythonJ-1.2.9.dist-info/top_level.txt
BythonJ-1.2.9.dist-info/RECORD
