Metadata-Version: 2.1
Name: BythonJ
Version: 1.2.9
Summary: Python interpreter allowing braces instead of colons
Author: Jaryl
Author-email: jaryl.ee.ry@gmail.com
Requires-Dist: pyinstaller
Requires-Dist: pynput
